redirectorbot-auth/__init__.py
redirectorbot-auth/auth.py
redirectorbot_auth/__init__.py
redirectorbot_auth/auth.py
redirectorbotAuth-0.1.5.dist-info/METADATA
redirectorbotAuth-0.1.5.dist-info/WHEEL
redirectorbotAuth-0.1.5.dist-info/top_level.txt
redirectorbotAuth-0.1.5.dist-info/RECORD
