Metadata-Version: 2.1
Name: redirectorbotAuth
Version: 0.1.5
Summary: Generate auth token for the Redirector Bot
Home-page: https://github.com/ncthuc/elastictools
Author: Redirector - Bot
License: MIT
Download-URL: https://pypi.org/project/elastictools/
Keywords: Redirector
Platform: UNKNOWN
Requires-Dist: python-dotenv
Requires-Dist: telethon
